informative_iterator/__init__.py
informative_iterator/settings.json
informative_iterator/__dependencies__/__init__.py
informative_iterator/__dependencies__/__pycache__/__init__.cpython-38.pyc
informative_iterator/__dependencies__/__sources__/file_system_py/.gitignore
informative_iterator/__dependencies__/__sources__/file_system_py/.gitrepo
informative_iterator/__dependencies__/__sources__/file_system_py/README.md
informative_iterator/__dependencies__/__sources__/file_system_py/poetry.lock
informative_iterator/__dependencies__/__sources__/file_system_py/pyproject.toml
informative_iterator/__dependencies__/__sources__/file_system_py/commands/pip
informative_iterator/__dependencies__/__sources__/file_system_py/commands/shell
informative_iterator/__dependencies__/__sources__/file_system_py/commands/start
informative_iterator/__dependencies__/__sources__/file_system_py/commands/subrepo
informative_iterator/__dependencies__/__sources__/file_system_py/commands/project/clean
informative_iterator/__dependencies__/__sources__/file_system_py/commands/project/commands
informative_iterator/__dependencies__/__sources__/file_system_py/commands/project/local_install
informative_iterator/__dependencies__/__sources__/file_system_py/commands/project/publish
informative_iterator/__dependencies__/__sources__/file_system_py/commands/project/purge
informative_iterator/__dependencies__/__sources__/file_system_py/documentation/fornix_framework.md
informative_iterator/__dependencies__/__sources__/file_system_py/documentation/setup.md
informative_iterator/__dependencies__/__sources__/file_system_py/documentation/images/cd_tutorial.gif
informative_iterator/__dependencies__/__sources__/file_system_py/documentation/images/package_from_example.png
informative_iterator/__dependencies__/__sources__/file_system_py/documentation/images/package_name.png
informative_iterator/__dependencies__/__sources__/file_system_py/documentation/images/package_versions.png
informative_iterator-2.2.3.dist-info/METADATA
informative_iterator-2.2.3.dist-info/WHEEL
informative_iterator-2.2.3.dist-info/top_level.txt
informative_iterator-2.2.3.dist-info/RECORD
