Metadata-Version: 2.1
Name: informative-iterator
Version: 2.2.3
Summary: A replacement for tqdm
Home-page: https://github.com/jeff-hykin/informative-iterator.git
Author: Jeff Hykin
Author-email: jeff.hykin@gmail.com
License: MIT
Platform: UNKNOWN
Requires-Python: >=3.6
